zrp/__init__.py
zrp/__main__.py
zrp/about.py
zrp/download.py
zrp/validate.py
zrp/zrp.py
zrp/data/processed/directionals_mapping.json
zrp/data/processed/inv_state_mapping.json
zrp/data/processed/lookup_tables_config.json
zrp/data/processed/misc_args.json
zrp/data/processed/standard_population_weights.json
zrp/data/processed/state_mapping.json
zrp/data/processed/street_suffix_mapping.json
zrp/data/processed/unit_mapping.json
zrp/modeling/__init__.py
zrp/modeling/feature_list_bg.json
zrp/modeling/feature_list_ct.json
zrp/modeling/feature_list_zp.json
zrp/modeling/performance.py
zrp/modeling/pipeline_builder.py
zrp/modeling/predict.py
zrp/modeling/models/__init__.py
zrp/modeling/models/block_group/__init__.py
zrp/modeling/models/block_group/model.txt
zrp/modeling/models/block_group/src/__init__.py
zrp/modeling/models/block_group/src/acs_scaler.py
zrp/modeling/models/block_group/src/app_fe.py
zrp/modeling/models/block_group/src/app_preprocessor.py
zrp/modeling/models/block_group/src/base_transform.py
zrp/modeling/models/block_group/src/set_key.py
zrp/modeling/models/census_tract/__init__.py
zrp/modeling/models/census_tract/model.txt
zrp/modeling/models/census_tract/src/__init__.py
zrp/modeling/models/census_tract/src/acs_scaler.py
zrp/modeling/models/census_tract/src/app_fe.py
zrp/modeling/models/census_tract/src/app_preprocessor.py
zrp/modeling/models/census_tract/src/base_transform.py
zrp/modeling/models/census_tract/src/set_key.py
zrp/modeling/models/zip_code/__init__.py
zrp/modeling/models/zip_code/model.txt
zrp/modeling/models/zip_code/src/__init__.py
zrp/modeling/models/zip_code/src/acs_scaler.py
zrp/modeling/models/zip_code/src/app_fe.py
zrp/modeling/models/zip_code/src/app_preprocessor.py
zrp/modeling/models/zip_code/src/base_transform.py
zrp/modeling/models/zip_code/src/set_key.py
zrp/modeling/src/__init__.py
zrp/modeling/src/acs_scaler.py
zrp/modeling/src/app_fe.py
zrp/modeling/src/app_preprocessor.py
zrp/modeling/src/base_transform.py
zrp-0.4.1.dist-info/LICENSE
zrp-0.4.1.dist-info/METADATA
zrp-0.4.1.dist-info/WHEEL
zrp-0.4.1.dist-info/top_level.txt
zrp-0.4.1.dist-info/RECORD
