Metadata-Version: 2.1
Name: zrp
Version: 0.4.1
Summary: The Zest Race Predictor tool predicts race/ethnicity using a name and address as inputs.
Home-page: https://github.com/zestai/zrp
Author: Kasey Matthews et al.
Author-email: abetterway@zest.ai
License: Apache-2.0
Keywords: race ethnicity names address acs geocode
Classifier: Development Status :: 4 - Beta
Classifier: Intended Audience :: Developers
Classifier: License :: OSI Approved :: Apache Software License
Classifier: Programming Language :: Python :: 3
Classifier: Programming Language :: Python :: 3.7
Classifier: Topic :: Scientific/Engineering :: Information Analysis
Classifier: Topic :: Software Development :: Libraries :: Python Modules
Classifier: Topic :: Utilities
License-File: LICENSE
Requires-Dist: category-encoders ==2.3.0
Requires-Dist: CensusData ==1.15
Requires-Dist: feature-engine ==1.2.0
Requires-Dist: fastparquet
Requires-Dist: joblib ==1.2.0
Requires-Dist: numpy
Requires-Dist: pandas ==1.2.5
Requires-Dist: plac ==1.3.4
Requires-Dist: pyarrow ==7.0.0
Requires-Dist: pycm ==3.3
Requires-Dist: scikit-learn ==1.0.2
Requires-Dist: surgeo ==1.1.2
Requires-Dist: tqdm ==4.46.0
Requires-Dist: xgboost ==1.0.2
